etherscan_shady/__init__.py
etherscan_shady/etherscan.py
etherscan_shady-0.1.1.dist-info/METADATA
etherscan_shady-0.1.1.dist-info/WHEEL
etherscan_shady-0.1.1.dist-info/RECORD
