Metadata-Version: 2.1
Name: etherscan_shady
Version: 0.1.1
Summary: Get balance erc20 and erc721 token of ethereum address
Project-URL: Homepage, https://github.com/shady273/Etherscan_API
Author-email: shady <taras2730@gmail.com>
Classifier: License :: OSI Approved :: MIT License
Classifier: Operating System :: OS Independent
Classifier: Programming Language :: Python :: 3
Requires-Python: >=3.7
